tests/__init__.py
tests/test_leitor.py
verificadorpdf/__init__.py
verificadorpdf/leitor.py
verificadorpdf-0.1.0.dist-info/METADATA
verificadorpdf-0.1.0.dist-info/WHEEL
verificadorpdf-0.1.0.dist-info/top_level.txt
verificadorpdf-0.1.0.dist-info/RECORD
