Metadata-Version: 2.4
Name: verificadorpdf
Version: 0.1.0
Summary: Um pacote para verificar palavras dentro de arquivos PDF
Home-page: https://github.com/Helio-Carmo/verificador-de-palavra-pdf.git
Author: Helio Carmo
Author-email: helio.h.carmo@gmail.com
Classifier: Programming Language :: Python :: 3
Classifier: Operating System :: OS Independent
Requires-Python: >=3.7
Requires-Dist: PyPDF2
Dynamic: author
Dynamic: author-email
Dynamic: classifier
Dynamic: description
Dynamic: description-content-type
Dynamic: home-page
Dynamic: requires-dist
Dynamic: requires-python
Dynamic: summary
